sqlite_manager_package/__init__.py
sqlite_manager_package/common_query.py
sqlite_manager_package/sqlite_manager.py
sqlite_manager_jp-0.0.2.dist-info/LICENSE
sqlite_manager_jp-0.0.2.dist-info/METADATA
sqlite_manager_jp-0.0.2.dist-info/WHEEL
sqlite_manager_jp-0.0.2.dist-info/top_level.txt
sqlite_manager_jp-0.0.2.dist-info/RECORD
