Metadata-Version: 2.1
Name: sqlite-manager-jp
Version: 0.0.2
Summary: A small package for sqlite executions
Home-page: https://github.com/Pinkwjp/sqlite_manager
Author: Jianping
Author-email: pinkwjp@gmail.com
License: UNKNOWN
Platform: UNKNOWN
Classifier: Programming Language :: Python :: 3
Classifier: License :: OSI Approved :: MIT License
Classifier: Operating System :: OS Independent
Requires-Python: >=3.9
License-File: LICENSE
